gutile-0.0.2.dist-info/pbr.json
gutile-0.0.2.dist-info/RECORD
gutile-0.0.2.dist-info/DESCRIPTION.rst
gutile-0.0.2.dist-info/top_level.txt
gutile-0.0.2.dist-info/WHEEL
gutile-0.0.2.dist-info/METADATA
gutile-0.0.2.dist-info/metadata.json
gutile/gfiles.py
gutile/_version.py
gutile/__init__.py
gutile/utils.py
