Metadata-Version: 2.0
Name: gutile
Version: 0.0.2
Summary: Shared google utils library.
Home-page: https://github.com/maybelinot/gutile
Author: Chris Ward
Author-email: cward@redhat.com
License: GPLv3
Download-URL: https://github.com/maybelinot/gutile/archive/master.zip
Keywords: information
Platform: UNKNOWN
Classifier: License :: OSI Approved :: GNU General Public License v3 (GPLv3)
Classifier: Natural Language :: English
Classifier: Programming Language :: Python :: 2.7
Classifier: Topic :: Office/Business
Classifier: Topic :: Utilities
Requires-Dist: argparse (==1.3.0)
Requires-Dist: google-api-python-client (==1.4.1)
Requires-Dist: oauth2client (>=1.4.12)
Provides-Extra: tests
Requires-Dist: pytest (==2.7.2); extra == 'tests'
